purpose.py
no_purpose_project-0.0.2.dist-info/METADATA
no_purpose_project-0.0.2.dist-info/WHEEL
no_purpose_project-0.0.2.dist-info/top_level.txt
no_purpose_project-0.0.2.dist-info/RECORD
